ROM/rom.vhd
library ieee;
use ieee.std_logic_1164.all;
use ieee.numeric_std.all;

entity rom is
	port( 	clk:		in std_logic;                              -- clock
			endereco:	in unsigned(6 downto 0) := "0000000";      -- endereço da ROM
			dado:		out unsigned(16 downto 0) := "00000000000000000" -- valor do endereço na ROM
		);
end entity;

architecture a_rom of rom is
	type mem is array (0 to 127) of unsigned (16 downto 0);    	-- De acordo com qual endereço estiver, ele vai mandar um valor
	constant conteudo_rom:	mem:=	(						   	-- para a saída da ROM, que vai para a UC e para os outros lugares do processador
		0  => "00000000000000000", -- 				NOP				0x00000
		1  => "00000000000000000", -- 				NOP				0x00000
		2  => "11110000101000000", -- 				JR tras			0x1E140
		3  => "00110000000000001", -- frente:		ADD r0, r6		0x06001
		4  => "01100000000001100", -- 				SUB r6, r9		0x0C00C
		5  => "00100001101000101", -- tras:			ADD 13, r7		0x04345
		6  => "00000000000000000", -- 				NOP				0x00000
		7  => "01100000000111001", -- 				SUB r12, r6		0x0C039
		8  => "11110000011000000", --				JR frente		0x1E0C0
		others => (others => '0')
	);	-- (r6 = 001(r1), r7 = 010(r2) e por assim vai)

begin
	process(clk)
	begin
		if(rising_edge(clk)) then
			dado <= conteudo_rom(to_integer(endereco));
		end if;
	end process;
end architecture;

Tarefa 4 - ROM/rom_tb.vhd
library ieee;
use ieee.std_logic_1164.all;
use ieee.numeric_std.all;

entity rom_tb is
end;

architecture a_rom_tb of rom_tb is
	component rom
		port( 	clk:		in std_logic;									 -- clock
				endereco:	in unsigned(6 downto 0) := "0000000";			 -- endereço da ROM
				dado:		out unsigned(16 downto 0) := "00000000000000000" -- valor do endereço da ROM
		);	
	end component;
	
	signal clk: 		std_logic;
	signal endereco: 	unsigned(6 downto 0) := "0000000";
	signal dado:		unsigned(16 downto 0) := "00000000000000000";
	
begin

	uut: rom port map(	clk => clk, 			-- Conectando as portas da ROM
						endereco => endereco,
						dado => dado
					);
	-- Início do tb da ROM
	process
	-- Rotina de clock
	begin
		clk <= '0';
		wait for 50 ns;
		
		clk <= '1';
		wait for 50 ns;
	
	end process;
	-- Rotina de teste
	process
	
	begin
	
		wait for 100 ns;
		
		endereco <= "0000000";
		wait for 100 ns;
		
		endereco <= "0000001";
		wait for 100 ns;
		
		endereco <= "0000010";
		wait for 100 ns;
		
		endereco <= "0000011";
		wait for 100 ns;
		
		endereco <= "0000100";
		wait for 100 ns;
		
		endereco <= "0000101";
		wait for 100 ns;
		
		endereco <= "0000110";
		wait for 100 ns;
		
		endereco <= "0000111";
		wait for 100 ns;
		
		endereco <= "0001000";
		wait for 100 ns;
		
		endereco <= "0000000";
		wait for 100 ns;
		
		endereco <= "0001010";
		wait for 100 ns;
		
				
		wait;
		
	end process;
end architecture;

ROM/rom.vcd
$date
  Fri Sep 04 10:30:49 2020
$end
$version
  GHDL v0
$end
$timescale
  1 fs
$end
$scope module standard $end
$upscope $end
$scope module std_logic_1164 $end
$upscope $end
$scope module numeric_std $end
$upscope $end
$scope module rom_tb $end
$var reg 1 ! clk $end
$var reg 7 " endereco[6:0] $end
$var reg 17 # dado[16:0] $end
$scope module uut $end
$var reg 1 $ clk $end
$var reg 7 % endereco[6:0] $end
$var reg 17 & dado[16:0] $end
$upscope $end
$upscope $end
$enddefinitions $end
#0
0!
b0000000 "
b00000000000000000 #
0$
b0000000 %
b00000000000000000 &
#50000000
1!
1$
#100000000
0!
0$
#150000000
1!
1$
#200000000
0!
b0000001 "
0$
b0000001 %
#250000000
1!
1$
#300000000
0!
b0000010 "
0$
b0000010 %
#350000000
1!
b11111110000000101 #
1$
b11111110000000101 &
#400000000
0!
b0000011 "
0$
b0000011 %
#450000000
1!
b00000110000000001 #
1$
b00000110000000001 &
#500000000
0!
b0000100 "
0$
b0000100 %
#550000000
1!
b00011000000100100 #
1$
b00011000000100100 &
#600000000
0!
b0000101 "
0$
b0000101 %
#650000000
1!
b00000110001000101 #
1$
b00000110001000101 &
#700000000
0!
b0000110 "
0$
b0000110 %
#750000000
1!
b00000000000000000 #
1$
b00000000000000000 &
#800000000
0!
b0000111 "
0$
b0000111 %
#850000000
1!
b00011000011100001 #
1$
b00011000011100001 &
#900000000
0!
b0011000 "
0$
b0011000 %
#950000000
1!
b00000000000000000 #
1$
b00000000000000000 &
#1000000000
0!
b0000000 "
0$
b0000000 %
