Máquina de Estados (2 estados)/maq_estados.vhd
library ieee;
use ieee.std_logic_1164.all;
use ieee.numeric_std.all;

entity maq_estados is
	port(	clk:	in std_logic;
			rst:	in std_logic;
			estado: out std_logic
		);
end entity;

architecture a_maq_estados of maq_estados is

	signal estado_int: std_logic;

begin

	process(clk,rst)
	begin
		if rst = '1' then
			estado_int <= '0';
		elsif(rising_edge(clk)) then
			estado_int <= not estado_int;
		end if;
	end process;
	estado <= estado_int;
end architecture;

Máquina de Estados(2 estados)/maq_estados_tb.vhd
library ieee;
use ieee.std_logic_1164.all;
use ieee.numeric_std.all;

entity maq_estados_tb is
end entity;

architecture a_maq_estados_tb of maq_estados_tb is
	component maq_estados
		port(	clk:	in std_logic;
				rst: 	in std_logic;
				estado: out std_logic
		);
	end component;
	
	signal clk, rst, estado: std_logic;
	
begin

	uut: maq_estados port map(	clk => clk,
								rst => rst,
								estado => estado
							);

	process
	
	begin
	
		clk <= '0';
		wait for 50 ns;
		
		clk <= '1';
		wait for 50 ns;
	
	end process;
	
	process
	
	begin
		
		rst <= '1';
		wait for 100 ns;
		
		rst <= '0';
		wait;
	end process;
end architecture;

Máquina de Estados(2 estados)/maq_estados.vcd
$date
  Fri Sep 04 12:38:28 2020
$end
$version
  GHDL v0
$end
$timescale
  1 fs
$end
$scope module standard $end
$upscope $end
$scope module std_logic_1164 $end
$upscope $end
$scope module numeric_std $end
$upscope $end
$scope module maq_estados_tb $end
$var reg 1 ! clk $end
$var reg 1 " rst $end
$var reg 1 # estado $end
$scope module uut $end
$var reg 1 $ clk $end
$var reg 1 % rst $end
$var reg 1 & estado $end
$var reg 1 ' estado_int $end
$upscope $end
$upscope $end
$enddefinitions $end
#0
0!
1"
0#
0$
1%
0&
0'
#50000000
1!
1$
#100000000
0!
0"
0$
0%
#150000000
1!
1#
1$
1&
1'
#200000000
0!
0$
#250000000
1!
0#
1$
0&
0'
#300000000
0!
0$
#350000000
1!
1#
1$
1&
1'
#400000000
0!
0$
#450000000
1!
0#
1$
0&
0'
#500000000
0!
0$
#550000000
1!
1#
1$
1&
1'
#600000000
0!
0$
#650000000
1!
0#
1$
0&
0'
#700000000
0!
0$
#750000000
1!
1#
1$
1&
1'
#800000000
0!
0$
#850000000
1!
0#
1$
0&
0'
#900000000
0!
0$
#950000000
1!
1#
1$
1&
1'
