Tarefa 3 - Banco de Registradores/registrador.vhd
library ieee;
use ieee.std_logic_1164.all;
use ieee.numeric_std.all;

entity registrador is
	port(	clk		:in std_logic; -- Porta do clock do registrador
			rst		:in std_logic; -- Porta do reset do registrador
			wr_en	:in std_logic; -- Porta do enable para escrever no registrador
			data_in	:in unsigned(15 downto 0):= "0000000000000000"; -- DATA da entrada do registrador
			
			data_out:out unsigned(15 downto 0):= "0000000000000000" -- DATA da saída do registrador
	);
end entity;

architecture a_registrador of registrador is
	signal registro: unsigned(15 downto 0); -- Memória do registrador
	
begin
	
	process(clk,rst,wr_en)
	begin
		if rst = '1' then -- Se o reset = 1, memória = 0x0000#
			registro <= "0000000000000000";
		elsif wr_en = '1' then -- Se o reset = 0 e o enable = 1
			if rising_edge(clk) then -- Na borda de subida do clock, registra a informação na entrada do registrador na memória
				registro <= data_in;
			end if;
		end if;
	end process;
	
	data_out <= registro;
end architecture;

Banco Registradores/bancoreg.vhd
library ieee;
use ieee.std_logic_1164.all;
use ieee.numeric_std.all;

entity bancoreg is
	port(	clk:		in std_logic; -- Porta do clock do banco
			rst: 		in std_logic; -- Porta do reset do banco
			write_en:	in std_logic; -- Porta do enable para escrever no banco de registradores
			sel_reg0:	in unsigned(2 downto 0):= "000"; -- Seletor para leitura do primeiro registrador
			sel_reg1:	in unsigned(2 downto 0):= "000"; -- Seletor para leitura do segundo registrador
			sel_wr_reg:	in unsigned(2 downto 0):= "000"; -- Seletor para escolher em qual registrador vai gravar a DATA
			datawr_reg:	in unsigned(15 downto 0):= "0000000000000000"; -- DATA para gravar no registrador
						
			data_reg0:	out unsigned(15 downto 0):= "0000000000000000"; -- DATA do primeiro registrador
			data_reg1:	out unsigned(15 downto 0):= "0000000000000000" -- DATA do segundo registrador
	);
end entity;

architecture a_bancoreg of bancoreg is
	component registrador is -- Criando o registrador dentro do banco
		port(	clk		:in std_logic; -- Porta do clock do registrador
				rst		:in std_logic; -- Porta do reset do registrador
				wr_en	:in std_logic; -- Porta do enable para escrever no registrador
				data_in	:in unsigned(15 downto 0):= "0000000000000000"; -- DATA da entrada do registrador
				
				data_out:out unsigned(15 downto 0):= "0000000000000000" -- DATA da saída do registrador
		);
	end component;
	
	signal 	out0, out1, out2, out3, out4, out5, out6, out7: unsigned(15 downto 0); -- Saída dos oito registradores do banco
	signal	en_0, en_1, en_2, en_3, en_4, en_5, en_6, en_7: std_logic; -- Enable dos oito registradores do banco
	
begin
	
	reg0: registrador port map(clk=>clk, rst=>rst, wr_en=>en_0, data_in=>datawr_reg, data_out=>out0); -- Linkando cada porta dos registradores com a porta dos bancos
	reg1: registrador port map(clk=>clk, rst=>rst, wr_en=>en_1, data_in=>datawr_reg, data_out=>out1); -- Tirando as portas de seletores de registrador
	reg2: registrador port map(clk=>clk, rst=>rst, wr_en=>en_2, data_in=>datawr_reg, data_out=>out2); 
	reg3: registrador port map(clk=>clk, rst=>rst, wr_en=>en_3, data_in=>datawr_reg, data_out=>out3);
	reg4: registrador port map(clk=>clk, rst=>rst, wr_en=>en_4, data_in=>datawr_reg, data_out=>out4);
	reg5: registrador port map(clk=>clk, rst=>rst, wr_en=>en_5, data_in=>datawr_reg, data_out=>out5);
	reg6: registrador port map(clk=>clk, rst=>rst, wr_en=>en_6, data_in=>datawr_reg, data_out=>out6);
	reg7: registrador port map(clk=>clk, rst=>rst, wr_en=>en_7, data_in=>datawr_reg, data_out=>out7);
	
	data_reg0 <=	"0000000000000000" when sel_reg0 = "000" else -- Quando selecionado o registrador para leitura, ele irá mandar a DATA gravada
					out1 when sel_reg0 = "001" else				  -- nele para a saída do banco. O registrador 0 sempre vai ter o valor 0x0000#, mesmo
					out2 when sel_reg0 = "010" else				  -- que tenha sido selecionado para escrever a DATA em sua memória.
					out3 when sel_reg0 = "011" else
					out4 when sel_reg0 = "100" else
					out5 when sel_reg0 = "101" else
					out6 when sel_reg0 = "110" else
					out7 when sel_reg0 = "111" else
					"0000000000000000";
					
	data_reg1 <= 	"0000000000000000" when sel_reg1 = "000" else
					out1 when sel_reg1 = "001" else
					out2 when sel_reg1 = "010" else
					out3 when sel_reg1 = "011" else
					out4 when sel_reg1 = "100" else
					out5 when sel_reg1 = "101" else
					out6 when sel_reg1 = "110" else
					out7 when sel_reg1 = "111" else
					"0000000000000000";
	
	en_1 <= '1' when write_en = '1' and sel_wr_reg = "001" else -- Tirando o registrador 0, se o enable da escrita do banco estiver ativo e o registrador
			'0';												-- estiver selecionado, vai ser gravado em sua memória a DATA da entrada
	en_2 <= '1' when write_en = '1' and sel_wr_reg = "010" else
			'0';
	en_3 <= '1' when write_en = '1' and sel_wr_reg = "011" else
			'0';
	en_4 <= '1' when write_en = '1' and sel_wr_reg = "100" else
			'0';
	en_5 <= '1' when write_en = '1' and sel_wr_reg = "101" else
			'0';
	en_6 <= '1' when write_en = '1' and sel_wr_reg = "110" else
			'0';
	en_7 <= '1' when write_en = '1' and sel_wr_reg = "111" else
			'0';
			
end architecture;

Banco Registradores/bancoreg_tb.vhd
library ieee;
use ieee.std_logic_1164.all;
use ieee.numeric_std.all;

entity bancoreg_tb is
end entity;

architecture a_bancoreg_tb of bancoreg_tb is
	component bancoreg
		port(	clk:		in std_logic; -- Porta do clock do banco
				rst: 		in std_logic; -- Porta do reset do banco
				write_en:	in std_logic; -- Porta do enable para escrever no banco de registradores
				sel_reg0:	in unsigned(2 downto 0):= "000"; -- Seletor para leitura do primeiro registrador
				sel_reg1:	in unsigned(2 downto 0):= "000"; -- Seletor para leitura do segundo registrador
				sel_wr_reg:	in unsigned(2 downto 0):= "000"; -- Seletor para escolher em qual registrador vai gravar a DATA
				datawr_reg:	in unsigned(15 downto 0):= "0000000000000000"; -- DATA para gravar no registrador
								
				data_reg0:	out unsigned(15 downto 0):= "0000000000000000"; -- DATA do primeiro registrador
				data_reg1:	out unsigned(15 downto 0):= "0000000000000000" -- DATA do segundo registrador
		);
	end component;
	
	signal datawr_reg, data_reg0, data_reg1: unsigned(15 downto 0):= "0000000000000000";
	signal sel_wr_reg, sel_reg0, sel_reg1: unsigned(2 downto 0):= "000";
	signal write_en, clk, rst: std_logic;
	
begin

	uut: bancoreg 	port map(	sel_reg0 => sel_reg0, -- Conectando as portas do banco
								sel_reg1 => sel_reg1,
								datawr_reg => datawr_reg,
								sel_wr_reg => sel_wr_reg,
								write_en => write_en,
								clk => clk,
								rst => rst,
								data_reg0 => data_reg0,
								data_reg1 => data_reg1
					);
	-- Início do tb do banco
	process
	-- Rotina do clock
	begin
		clk <= '0';
		wait for 50 ns;
		clk <= '1';
		wait for 50 ns;
	end process;
	
	process
	-- Rotina de inicialização
	begin
		rst <= '1';
		wait for 100 ns;
		rst <= '0';
		wait;
	end process;
	
	process
	-- Rotina de teste no banco
	begin
		write_en <= '0'; -- Desativando o enable
		sel_reg0 <= "000"; -- Lendo o registrador 0 na primeira saída
		sel_reg1 <= "010"; -- Lendo o registrador 2 na segunda saída
		sel_wr_reg <= "001"; -- Selecionando o registrador 1 para escrita
		datawr_reg <= "0101010110101010"; -- DATA para escrever no registrador = 0x55AA#
		wait for 100 ns; -- Espera a rotina de inicialização
		
		write_en <= '1'; -- Ativa o enable, permitindo a escrita no registrador selecionado (registrador 1)
		datawr_reg <= "1010101001010101"; -- DATA para escrever no registrador = 0xAA55#
		wait for 100 ns;
		
		write_en <= '0'; -- Desativando o enable
		sel_reg1 <= "001"; -- Lendo o registrador 1 na segunda saída
		sel_wr_reg <= "000"; -- Selecionando o registrador 0 para escrita
		datawr_reg <= "1111111111111111"; -- DATA para escrever no registrador = 0xFFFF#
		wait for 100 ns;
		
		write_en <= '1'; -- Ativa o enable, mas não escreve no registrador selecionado (registrador 0)
		wait for 100 ns;
		
		sel_wr_reg <= "100"; -- Selecionando o registrador 4 para escrita
		datawr_reg <= "0000000000000011"; -- DATA para escrever no registrador = 0x0003#
		wait for 100 ns;
		
		write_en <= '0'; -- Desativando o enable
		sel_reg0 <= "001"; -- Lendo o registrador 1 na primeira saída
		sel_reg1 <= "100"; -- Lendo o registrador 4 na segunda saída
		datawr_reg <= "0000000000000000"; -- DATA para escrever no registrador = 0x0000#
		wait for 100 ns;
		
		wait;
	end process;
	
end architecture;

Banco Registradores/bancoreg.vcd
$date
  Wed Aug 19 12:35:20 2020
$end
$version
  GHDL v0
$end
$timescale
  1 fs
$end
$scope module standard $end
$upscope $end
$scope module std_logic_1164 $end
$upscope $end
$scope module numeric_std $end
$upscope $end
$scope module bancoreg_tb $end
$var reg 16 ! datawr_reg[15:0] $end
$var reg 16 " data_reg0[15:0] $end
$var reg 16 # data_reg1[15:0] $end
$var reg 3 $ sel_wr_reg[2:0] $end
$var reg 3 % sel_reg0[2:0] $end
$var reg 3 & sel_reg1[2:0] $end
$var reg 1 ' write_en $end
$var reg 1 ( clk $end
$var reg 1 ) rst $end
$scope module uut $end
$var reg 1 * clk $end
$var reg 1 + rst $end
$var reg 1 , write_en $end
$var reg 3 - sel_reg0[2:0] $end
$var reg 3 . sel_reg1[2:0] $end
$var reg 3 / sel_wr_reg[2:0] $end
$var reg 16 0 datawr_reg[15:0] $end
$var reg 16 1 data_reg0[15:0] $end
$var reg 16 2 data_reg1[15:0] $end
$var reg 16 3 out0[15:0] $end
$var reg 16 4 out1[15:0] $end
$var reg 16 5 out2[15:0] $end
$var reg 16 6 out3[15:0] $end
$var reg 16 7 out4[15:0] $end
$var reg 16 8 out5[15:0] $end
$var reg 16 9 out6[15:0] $end
$var reg 16 : out7[15:0] $end
$var reg 1 ; en_0 $end
$var reg 1 < en_1 $end
$var reg 1 = en_2 $end
$var reg 1 > en_3 $end
$var reg 1 ? en_4 $end
$var reg 1 @ en_5 $end
$var reg 1 A en_6 $end
$var reg 1 B en_7 $end
$scope module reg0 $end
$var reg 1 C clk $end
$var reg 1 D rst $end
$var reg 1 E wr_en $end
$var reg 16 F data_in[15:0] $end
$var reg 16 G data_out[15:0] $end
$var reg 16 H registro[15:0] $end
$upscope $end
$scope module reg1 $end
$var reg 1 I clk $end
$var reg 1 J rst $end
$var reg 1 K wr_en $end
$var reg 16 L data_in[15:0] $end
$var reg 16 M data_out[15:0] $end
$var reg 16 N registro[15:0] $end
$upscope $end
$scope module reg2 $end
$var reg 1 O clk $end
$var reg 1 P rst $end
$var reg 1 Q wr_en $end
$var reg 16 R data_in[15:0] $end
$var reg 16 S data_out[15:0] $end
$var reg 16 T registro[15:0] $end
$upscope $end
$scope module reg3 $end
$var reg 1 U clk $end
$var reg 1 V rst $end
$var reg 1 W wr_en $end
$var reg 16 X data_in[15:0] $end
$var reg 16 Y data_out[15:0] $end
$var reg 16 Z registro[15:0] $end
$upscope $end
$scope module reg4 $end
$var reg 1 [ clk $end
$var reg 1 \ rst $end
$var reg 1 ] wr_en $end
$var reg 16 ^ data_in[15:0] $end
$var reg 16 _ data_out[15:0] $end
$var reg 16 ` registro[15:0] $end
$upscope $end
$scope module reg5 $end
$var reg 1 a clk $end
$var reg 1 b rst $end
$var reg 1 c wr_en $end
$var reg 16 d data_in[15:0] $end
$var reg 16 e data_out[15:0] $end
$var reg 16 f registro[15:0] $end
$upscope $end
$scope module reg6 $end
$var reg 1 g clk $end
$var reg 1 h rst $end
$var reg 1 i wr_en $end
$var reg 16 j data_in[15:0] $end
$var reg 16 k data_out[15:0] $end
$var reg 16 l registro[15:0] $end
$upscope $end
$scope module reg7 $end
$var reg 1 m clk $end
$var reg 1 n rst $end
$var reg 1 o wr_en $end
$var reg 16 p data_in[15:0] $end
$var reg 16 q data_out[15:0] $end
$var reg 16 r registro[15:0] $end
$upscope $end
$upscope $end
$upscope $end
$enddefinitions $end
#0
b0101010110101010 !
b0000000000000000 "
b0000000000000000 #
b001 $
b000 %
b010 &
0'
0(
1)
0*
1+
0,
b000 -
b010 .
b001 /
b0101010110101010 0
b0000000000000000 1
b0000000000000000 2
b0000000000000000 3
b0000000000000000 4
b0000000000000000 5
b0000000000000000 6
b0000000000000000 7
b0000000000000000 8
b0000000000000000 9
b0000000000000000 :
U;
0<
0=
0>
0?
0@
0A
0B
0C
1D
UE
b0101010110101010 F
b0000000000000000 G
b0000000000000000 H
0I
1J
0K
b0101010110101010 L
b0000000000000000 M
b0000000000000000 N
0O
1P
0Q
b0101010110101010 R
b0000000000000000 S
b0000000000000000 T
0U
1V
0W
b0101010110101010 X
b0000000000000000 Y
b0000000000000000 Z
0[
1\
0]
b0101010110101010 ^
b0000000000000000 _
b0000000000000000 `
0a
1b
0c
b0101010110101010 d
b0000000000000000 e
b0000000000000000 f
0g
1h
0i
b0101010110101010 j
b0000000000000000 k
b0000000000000000 l
0m
1n
0o
b0101010110101010 p
b0000000000000000 q
b0000000000000000 r
#50000000
1(
1*
1C
1I
1O
1U
1[
1a
1g
1m
#100000000
b1010101001010101 !
1'
0(
0)
0*
0+
1,
b1010101001010101 0
1<
0C
0D
b1010101001010101 F
0I
0J
1K
b1010101001010101 L
0O
0P
b1010101001010101 R
0U
0V
b1010101001010101 X
0[
0\
b1010101001010101 ^
0a
0b
b1010101001010101 d
0g
0h
b1010101001010101 j
0m
0n
b1010101001010101 p
#150000000
1(
1*
b1010101001010101 4
1C
1I
b1010101001010101 M
b1010101001010101 N
1O
1U
1[
1a
1g
1m
#200000000
b1111111111111111 !
b1010101001010101 #
b000 $
b001 &
0'
0(
0*
0,
b001 .
b000 /
b1111111111111111 0
b1010101001010101 2
0<
0C
b1111111111111111 F
0I
0K
b1111111111111111 L
0O
b1111111111111111 R
0U
b1111111111111111 X
0[
b1111111111111111 ^
0a
b1111111111111111 d
0g
b1111111111111111 j
0m
b1111111111111111 p
#250000000
1(
1*
1C
1I
1O
1U
1[
1a
1g
1m
#300000000
1'
0(
0*
1,
0C
0I
0O
0U
0[
0a
0g
0m
#350000000
1(
1*
1C
1I
1O
1U
1[
1a
1g
1m
#400000000
b0000000000000011 !
b100 $
0(
0*
b100 /
b0000000000000011 0
1?
0C
b0000000000000011 F
0I
b0000000000000011 L
0O
b0000000000000011 R
0U
b0000000000000011 X
0[
1]
b0000000000000011 ^
0a
b0000000000000011 d
0g
b0000000000000011 j
0m
b0000000000000011 p
#450000000
1(
1*
b0000000000000011 7
1C
1I
1O
1U
1[
b0000000000000011 _
b0000000000000011 `
1a
1g
1m
#500000000
b0000000000000000 !
b1010101001010101 "
b0000000000000011 #
b001 %
b100 &
0'
0(
0*
0,
b001 -
b100 .
b0000000000000000 0
b1010101001010101 1
b0000000000000011 2
0?
0C
b0000000000000000 F
0I
b0000000000000000 L
0O
b0000000000000000 R
0U
b0000000000000000 X
0[
0]
b0000000000000000 ^
0a
b0000000000000000 d
0g
b0000000000000000 j
0m
b0000000000000000 p
