Tarefa 3 - Banco de Registradores/registrador.vhd
library ieee;
use ieee.std_logic_1164.all;
use ieee.numeric_std.all;

entity registrador is
	port(	clk		:in std_logic; -- Porta do clock do registrador
			rst		:in std_logic; -- Porta do reset do registrador
			wr_en	:in std_logic; -- Porta do enable para escrever no registrador
			data_in	:in unsigned(15 downto 0):= "0000000000000000"; -- DATA da entrada do registrador
			
			data_out:out unsigned(15 downto 0):= "0000000000000000" -- DATA da saída do registrador
	);
end entity;

architecture a_registrador of registrador is
	signal registro: unsigned(15 downto 0); -- Memória do registrador
	
begin
	
	process(clk,rst,wr_en)
	begin
		if rst = '1' then -- Se o reset = 1, memória = 0x0000#
			registro <= "0000000000000000";
		elsif wr_en = '1' then -- Se o reset = 0 e o enable = 1
			if rising_edge(clk) then -- Na borda de subida do clock, registra a informação na entrada do registrador na memória
				registro <= data_in;
			end if;
		end if;
	end process;
	
	data_out <= registro;
end architecture;

Tarefa 3 - Banco de Registradores/registrador_tb.vhd
library ieee;
use ieee.std_logic_1164.all;
use ieee.numeric_std.all;

entity registrador_tb is
end;

architecture a_registrador_tb of registrador_tb is
	component registrador
		port(	clk		:in std_logic; -- Porta de clock
				rst		:in std_logic; -- Porta do reset
				wr_en	:in std_logic; -- Porta do enable para escrever no registrador
				data_in	:in unsigned(15 downto 0); -- Informação na entrada do registrador
				
				data_out:out unsigned(15 downto 0) -- Informação na saída do registrador
		);
	end component;
	
	signal clk, rst, wr_en: std_logic;
	signal data_in, data_out: unsigned(15 downto 0);
	
begin
	
	uut: registrador port map(	clk => clk, -- Conectando as portas do registrador
								rst => rst,
								wr_en => wr_en,
								data_in => data_in,
								data_out => data_out
							);
	-- Início do tb do registrador
	process
	-- Rotina do clock
	begin
		clk <= '0'; 
		wait for 50 ns;
		
		clk <= '1';
		wait for 50 ns;
		
	end process;
	
	process
	-- Rotina de inicialização
	begin
		rst <= '1';
		wait for 100 ns;
		
		rst <= '0';
		
		wait;
	end process;
	
	process
	-- Rotina de teste do registrador
	begin
		wait for 100 ns; -- Espera a inicialização
		wr_en <= '0'; -- Enable desativado, não escreve na memória
		data_in <= "1111111111111111"; -- DATA da entrada = 0xFFFF#
		wait for 100 ns;
		
		data_in <= "1001100110010100"; -- DATA da entrada = 0x9994#
		wr_en <= '1'; -- Enable ativado, escreve na memória
		wait for 100 ns;
		
		data_in <= "0000110001101011"; -- DATA na entrada = 0x0C6B#
		wr_en <= '0'; -- Enable desativado, não escreve na memória
		wait for 100 ns;
		
		wr_en <= '1'; -- Enable ativado, escreve na memória
		wait for 100 ns;
		
		data_in <= "1010101011000011"; -- DATA na entrada = 0xAAC3#
		wr_en <= '0'; -- Enable desativado, não escreve na memória
		wait for 1000 ns;
		
		wr_en <= '1'; -- Enable ativado, escreve na memória
		wait for 100 ns;
		
		data_in <= "1000000000000001"; -- DATA na entrada = 0x8001#
		wr_en <= '0'; -- Enable desativado, não escreve na memória
		wait for 100 ns;
		
		wait;
		
	end process;
end architecture;

Banco Registradores/registrador.vcd
$date
  Wed Aug 19 12:13:59 2020
$end
$version
  GHDL v0
$end
$timescale
  1 fs
$end
$scope module standard $end
$upscope $end
$scope module std_logic_1164 $end
$upscope $end
$scope module numeric_std $end
$upscope $end
$scope module registrador_tb $end
$var reg 1 ! clk $end
$var reg 1 " rst $end
$var reg 1 # wr_en $end
$var reg 16 $ data_in[15:0] $end
$var reg 16 % data_out[15:0] $end
$scope module uut $end
$var reg 1 & clk $end
$var reg 1 ' rst $end
$var reg 1 ( wr_en $end
$var reg 16 ) data_in[15:0] $end
$var reg 16 * data_out[15:0] $end
$var reg 16 + registro[15:0] $end
$upscope $end
$upscope $end
$enddefinitions $end
#0
0!
1"
U#
bUUUUUUUUUUUUUUUU $
b0000000000000000 %
0&
1'
U(
bUUUUUUUUUUUUUUUU )
b0000000000000000 *
b0000000000000000 +
#50000000
1!
1&
#100000000
0!
0"
0#
b1111111111111111 $
0&
0'
0(
b1111111111111111 )
#150000000
1!
1&
#200000000
0!
1#
b1001100110010100 $
0&
1(
b1001100110010100 )
#250000000
1!
b1001100110010100 %
1&
b1001100110010100 *
b1001100110010100 +
#300000000
0!
0#
b0000110001101011 $
0&
0(
b0000110001101011 )
#350000000
1!
1&
#400000000
0!
1#
0&
1(
#450000000
1!
b0000110001101011 %
1&
b0000110001101011 *
b0000110001101011 +
#500000000
0!
0#
b1010101011000011 $
0&
0(
b1010101011000011 )
#550000000
1!
1&
#600000000
0!
0&
#650000000
1!
1&
#700000000
0!
0&
#750000000
1!
1&
#800000000
0!
0&
#850000000
1!
1&
#900000000
0!
0&
#950000000
1!
1&
#1000000000
0!
0&
#1050000000
1!
1&
#1100000000
0!
0&
#1150000000
1!
1&
#1200000000
0!
0&
#1250000000
1!
1&
#1300000000
0!
0&
#1350000000
1!
1&
#1400000000
0!
0&
#1450000000
1!
1&
#1500000000
0!
1#
0&
1(
#1550000000
1!
b1010101011000011 %
1&
b1010101011000011 *
b1010101011000011 +
#1600000000
0!
0#
b1000000000000001 $
0&
0(
b1000000000000001 )
