Tarefa 2 - ULA/ula.vhd
library ieee;
use ieee.std_logic_1164.all;
use ieee.numeric_std.all;

entity ula is
    port(	op: in std_logic_vector (1 downto 0); -- Porta seletora da operação da ULA
			in_a, in_b: in unsigned (15 downto 0) := "0000000000000000"; -- Entradas de DATA A e B da ULA

			out_a: out unsigned (15 downto 0) := "0000000000000000"; -- Saída com o resultado da operação da ULA (soma/subtração)
			out_b: out std_logic -- Saída lógica com o resultado da operação da ULA (Comparação)
    );
end entity;

architecture a_ula of ula is
begin
	--Se for alguma das operações soma/subtração
    out_a <=  in_a + in_b when op = "00" else -- Saída = soma das portas A e B
			  in_a - in_b when op = "01" else -- Saída = subtração das portas A e B
              "0000000000000000";
	-- Se for alguma das comparações		  
	out_b <=  '1' when in_a < in_b and op = "10" else -- Saída = 1 se B > A
			  '1' when in_a > in_b and op = "11" else -- Saída = 1 se A > B
			  '0';
end architecture;

Tarefa 3 - Banco de Registradores/ula_tb.vhd
library ieee;
use ieee.std_logic_1164.all;
use ieee.numeric_std.all;

entity ula_tb is
end;

architecture a_ula_tb of ula_tb is
    component ula
        port(	op: in std_logic_vector (1 downto 0); -- Porta seletora da operação da ULA
				in_a, in_b: in unsigned (15 downto 0) := "0000000000000000"; -- Entradas de DATA A e B da ULA

				out_a: out unsigned (15 downto 0) := "0000000000000000"; -- Saída com o resultado da operação da ULA (soma/subtração)
				out_b: out std_logic -- Saída lógica com o resultado da operação da ULA (Comparação)
		);
    end component;
	signal op: std_logic_vector (1 downto 0);
    signal in_a, in_b, out_a: unsigned (15 downto 0) := "0000000000000000";
	signal out_b: std_logic;
    
begin
    uut: ula port map( -- Conectando as portas da ULA
        in_a => in_a,
        in_b => in_b,
        out_a => out_a,
		out_b => out_b,
        op => op
    );
	-- Início do tb da ULA
    process
	-- Rotina de teste
    begin
        in_a <= "0000000000000001"; -- Informação na porta A = 0x0001#
        in_b <= "0000000000000011"; -- Informação na porta B = 0x0003#
        op <= "00"; -- Operação soma
        wait for 50 ns;

        in_a <= "0000000000000011"; -- Informação na porta A = 0x0003#
        in_b <= "0000000000000001"; -- Informação na porta B = 0x0001#
        op <= "01"; -- Operação subtração
        wait for 50 ns;

        in_a <= "0000000000000001"; -- Informação na porta A = 0x0001#
        in_b <= "0000000000000011"; -- Informação na porta B = 0x0003#
        op <= "10"; -- Operação compara se A < B
        wait for 50 ns;

        in_a <= "0000000000000011"; -- Informação na porta B = 0x0003#
        in_b <= "0000000000000001"; -- Informação na porta A = 0x0001#
        op <= "10"; -- Operação compara se A < B
        wait for 50 ns;

        in_a <= "0000000000000011"; -- Informação na porta B = 0x0003#
        in_b <= "0000000000000011"; -- Informação na porta B = 0x0003#
        op <= "10"; -- Operação compara se A < B
        wait for 50 ns;

        in_a <= "0000000000000001"; -- Informação na porta A = 0x0001#
        in_b <= "0000000000000011"; -- Informação na porta B = 0x0003#
        op <= "11"; -- Operação compara se A > B
        wait for 50 ns;

        in_a <= "0000000000000011"; -- Informação na porta B = 0x0003#
        in_b <= "0000000000000001"; -- Informação na porta A = 0x0001#
        op <= "11"; -- Operação compara se A > B
        wait for 50 ns;

        in_a <= "0000000000000011"; -- Informação na porta B = 0x0003#
        in_b <= "0000000000000011"; -- Informação na porta B = 0x0003#
        op <= "11"; -- Operação compara se A > B
        wait for 50 ns;

        wait;
    end process;
end architecture;

Tarefa 3 - Banco de Registradores/ula.vcd
$date
  Wed Aug 19 12:12:44 2020
$end
$version
  GHDL v0
$end
$timescale
  1 fs
$end
$scope module standard $end
$upscope $end
$scope module std_logic_1164 $end
$upscope $end
$scope module numeric_std $end
$upscope $end
$scope module ula_tb $end
$var reg 2 ! op[1:0] $end
$var reg 16 " in_a[15:0] $end
$var reg 16 # in_b[15:0] $end
$var reg 16 $ out_a[15:0] $end
$var reg 1 % out_b $end
$scope module uut $end
$var reg 2 & op[1:0] $end
$var reg 16 ' in_a[15:0] $end
$var reg 16 ( in_b[15:0] $end
$var reg 16 ) out_a[15:0] $end
$var reg 1 * out_b $end
$upscope $end
$upscope $end
$enddefinitions $end
#0
b00 !
b0000000000000001 "
b0000000000000011 #
b0000000000000100 $
0%
b00 &
b0000000000000001 '
b0000000000000011 (
b0000000000000100 )
0*
#50000000
b01 !
b0000000000000011 "
b0000000000000001 #
b0000000000000010 $
b01 &
b0000000000000011 '
b0000000000000001 (
b0000000000000010 )
#100000000
b10 !
b0000000000000001 "
b0000000000000011 #
b0000000000000000 $
1%
b10 &
b0000000000000001 '
b0000000000000011 (
b0000000000000000 )
1*
#150000000
b0000000000000011 "
b0000000000000001 #
0%
b0000000000000011 '
b0000000000000001 (
0*
#200000000
b0000000000000011 #
b0000000000000011 (
#250000000
b11 !
b0000000000000001 "
b11 &
b0000000000000001 '
#300000000
b0000000000000011 "
b0000000000000001 #
1%
b0000000000000011 '
b0000000000000001 (
1*
#350000000
b0000000000000011 #
0%
b0000000000000011 (
0*
