PC/pc.vhd
library ieee;
use ieee.std_logic_1164.all;
use ieee.numeric_std.all;

entity pc is
	port(	clk		:in std_logic; -- Porta do clock do pc
			rst		:in std_logic; -- Porta do reset do pc
			wr_en	:in std_logic; -- Porta do enable para escrever no pc
			data_in	:in unsigned(6 downto 0):= "0000000"; -- DATA da entrada do pc

			data_out:out unsigned(6 downto 0):= "0000000" -- DATA da saída do pc
	);
end entity;

architecture a_pc of pc is
	signal registro: unsigned(6 downto 0); -- Memória do pc

begin

	process(clk,rst,wr_en)
	begin
		if rst = '1' then -- Se o reset = 1, memória = 0x0000#
			registro <= "0000000";
		elsif wr_en = '1' then -- Se o reset = 0 e o enable = 1
			if rising_edge(clk) then -- Na borda de subida do clock, registra a informação na entrada do pc na memória
				registro <= data_in;
			end if;
		end if;
	end process;

	data_out <= registro;
end architecture;

PC/pc_tb.vhd
library ieee;
use ieee.std_logic_1164.all;
use ieee.numeric_std.all;

entity pc_tb is
end;

architecture a_pc_tb of pc_tb is
	component pc
		port(	clk		:in std_logic; -- Porta de clock
				rst		:in std_logic; -- Porta do reset
				wr_en	:in std_logic; -- Porta do enable para escrever no pc
				data_in	:in unsigned(6 downto 0); -- Informação na entrada do pc

				data_out:out unsigned(6 downto 0) -- Informação na saída do pc
		);
	end component;

	signal clk, rst, wr_en: std_logic;
	signal data_in, data_out: unsigned(6 downto 0);

begin

	uut: pc port map(	clk => clk, -- Conectando as portas do pc
								rst => rst,
								wr_en => wr_en,
								data_in => data_in,
								data_out => data_out
							);
	-- Início do tb do pc
	process
	-- Rotina do clock
	begin
		clk <= '0';
		wait for 50 ns;

		clk <= '1';
		wait for 50 ns;

	end process;

	process
	-- Rotina de inicialização
	begin
		rst <= '1';
		wait for 100 ns;

		rst <= '0';

		wait;
	end process;

	process
	-- Rotina de teste do pc
	begin
		wait for 100 ns; -- Espera a inicialização
		wr_en <= '0'; -- Enable desativado, não escreve na memória
		data_in <= "1111111"; -- DATA da entrada = 0xFFFF#
		wait for 100 ns;

		data_in <= "0010100"; -- DATA da entrada = 0x9994#
		wr_en <= '1'; -- Enable ativado, escreve na memória
		wait for 100 ns;

		data_in <= "1101011"; -- DATA na entrada = 0x0C6B#
		wr_en <= '0'; -- Enable desativado, não escreve na memória
		wait for 100 ns;

		wr_en <= '1'; -- Enable ativado, escreve na memória
		wait for 100 ns;

		data_in <= "1000011"; -- DATA na entrada = 0xAAC3#
		wr_en <= '0'; -- Enable desativado, não escreve na memória
		wait for 1000 ns;

		wr_en <= '1'; -- Enable ativado, escreve na memória
		wait for 100 ns;

		data_in <= "0000001"; -- DATA na entrada = 0x8001#
		wr_en <= '0'; -- Enable desativado, não escreve na memória
		wait for 100 ns;

		wait;

	end process;
end architecture;

PC/pc.vcd
$date
  Fri Sep 04 19:32:52 2020
$end
$version
  GHDL v0
$end
$timescale
  1 fs
$end
$scope module standard $end
$upscope $end
$scope module std_logic_1164 $end
$upscope $end
$scope module numeric_std $end
$upscope $end
$scope module pc_tb $end
$var reg 1 ! clk $end
$var reg 1 " rst $end
$var reg 1 # wr_en $end
$var reg 7 $ data_in[6:0] $end
$var reg 7 % data_out[6:0] $end
$scope module uut $end
$var reg 1 & clk $end
$var reg 1 ' rst $end
$var reg 1 ( wr_en $end
$var reg 7 ) data_in[6:0] $end
$var reg 7 * data_out[6:0] $end
$var reg 7 + registro[6:0] $end
$upscope $end
$upscope $end
$enddefinitions $end
#0
0!
1"
U#
bUUUUUUU $
b0000000 %
0&
1'
U(
bUUUUUUU )
b0000000 *
b0000000 +
#50000000
1!
1&
#100000000
0!
0"
0#
b1111111 $
0&
0'
0(
b1111111 )
#150000000
1!
1&
#200000000
0!
1#
b0010100 $
0&
1(
b0010100 )
#250000000
1!
b0010100 %
1&
b0010100 *
b0010100 +
#300000000
0!
0#
b1101011 $
0&
0(
b1101011 )
#350000000
1!
1&
#400000000
0!
1#
0&
1(
#450000000
1!
b1101011 %
1&
b1101011 *
b1101011 +
#500000000
0!
0#
b1000011 $
0&
0(
b1000011 )
#550000000
1!
1&
#600000000
0!
0&
#650000000
1!
1&
#700000000
0!
0&
#750000000
1!
1&
#800000000
0!
0&
#850000000
1!
1&
#900000000
0!
0&
#950000000
1!
1&
#1000000000
0!
0&
#1050000000
1!
1&
#1100000000
0!
0&
#1150000000
1!
1&
#1200000000
0!
0&
#1250000000
1!
1&
#1300000000
0!
0&
#1350000000
1!
1&
#1400000000
0!
0&
#1450000000
1!
1&
#1500000000
0!
1#
0&
1(
#1550000000
1!
b1000011 %
1&
b1000011 *
b1000011 +
#1600000000
0!
0#
b0000001 $
0&
0(
b0000001 )
